dremio_cli/__init__.py
dremio_cli/__main__.py
dremio_cli/cli.py
dremio_cli/config.py
dremio_cli/env.py
dremio_cli/history.py
dremio_cli/client/__init__.py
dremio_cli/client/auth.py
dremio_cli/client/base.py
dremio_cli/client/cloud.py
dremio_cli/client/factory.py
dremio_cli/client/software.py
dremio_cli/commands/__init__.py
dremio_cli/commands/catalog.py
dremio_cli/commands/completion.py
dremio_cli/commands/favorite.py
dremio_cli/commands/folder.py
dremio_cli/commands/grant.py
dremio_cli/commands/history.py
dremio_cli/commands/init.py
dremio_cli/commands/job.py
dremio_cli/commands/lineage.py
dremio_cli/commands/monitor.py
dremio_cli/commands/profile.py
dremio_cli/commands/reflection.py
dremio_cli/commands/repl.py
dremio_cli/commands/role.py
dremio_cli/commands/script.py
dremio_cli/commands/source.py
dremio_cli/commands/space.py
dremio_cli/commands/sql.py
dremio_cli/commands/sync.py
dremio_cli/commands/table.py
dremio_cli/commands/tag.py
dremio_cli/commands/udf.py
dremio_cli/commands/ui.py
dremio_cli/commands/user.py
dremio_cli/commands/view.py
dremio_cli/commands/wiki.py
dremio_cli/dac/__init__.py
dremio_cli/dac/config.py
dremio_cli/dac/diff.py
dremio_cli/dac/graph.py
dremio_cli/dac/state.py
dremio_cli/dac/sync.py
dremio_cli/formatters/__init__.py
dremio_cli/formatters/json.py
dremio_cli/formatters/table.py
dremio_cli/formatters/yaml.py
dremio_cli/tui/catalog/__init__.py
dremio_cli/tui/catalog/app.py
dremio_cli/tui/catalog/screens.py
dremio_cli/tui/catalog/widgets.py
dremio_cli/utils/__init__.py
dremio_cli/utils/console.py
dremio_cli/utils/exceptions.py
dremio_cli/utils/helpers.py
dremio_cli/utils/validators.py
dremio_cli-1.11.0.dist-info/licenses/LICENSE
dremio_cli-1.11.0.dist-info/METADATA
dremio_cli-1.11.0.dist-info/WHEEL
dremio_cli-1.11.0.dist-info/entry_points.txt
dremio_cli-1.11.0.dist-info/top_level.txt
dremio_cli-1.11.0.dist-info/RECORD
