Metadata-Version: 2.4
Name: dremio-cli
Version: 1.11.0
Summary: A comprehensive command-line interface for Dremio Cloud and Dremio Software
Home-page: https://github.com/your-org/dremio-cli
Author: Your Name
Author-email: Dremio Developer Advocacy <developer-advocacy@dremio.com>
Maintainer-email: Dremio Developer Advocacy <developer-advocacy@dremio.com>
License: Apache-2.0
Project-URL: Homepage, https://github.com/developer-advocacy-dremio/dremio-python-cli
Project-URL: Documentation, https://github.com/developer-advocacy-dremio/dremio-python-cli/tree/main/dremio-cli/docs
Project-URL: Repository, https://github.com/developer-advocacy-dremio/dremio-python-cli
Project-URL: Issues, https://github.com/developer-advocacy-dremio/dremio-python-cli/issues
Project-URL: Changelog, https://github.com/developer-advocacy-dremio/dremio-python-cli/releases
Keywords: dremio,cli,data,lakehouse,sql,analytics,cloud,data-engineering
Classifier: Development Status :: 5 - Production/Stable
Classifier: Intended Audience :: Developers
Classifier: Intended Audience :: System Administrators
Classifier: License :: OSI Approved :: Apache Software License
Classifier: Operating System :: OS Independent
Classifier: Programming Language :: Python :: 3
Classifier: Programming Language :: Python :: 3.8
Classifier: Programming Language :: Python :: 3.9
Classifier: Programming Language :: Python :: 3.10
Classifier: Programming Language :: Python :: 3.11
Classifier: Programming Language :: Python :: 3.12
Classifier: Topic :: Database
Classifier: Topic :: Software Development :: Libraries :: Python Modules
Classifier: Topic :: System :: Systems Administration
Classifier: Topic :: Utilities
Requires-Python: >=3.9
License-File: LICENSE
Requires-Dist: click>=8.0.0
Requires-Dist: requests>=2.28.0
Requires-Dist: rich>=13.0.0
Requires-Dist: python-dotenv>=1.0.0
Requires-Dist: pyyaml>=6.0.0
Requires-Dist: prompt_toolkit>=3.0.0
Requires-Dist: textual>=0.40.0
Requires-Dist: pandas>=2.0.0
Requires-Dist: pyarrow>=12.0.0
Provides-Extra: dev
Requires-Dist: pytest>=7.0.0; extra == "dev"
Requires-Dist: pytest-asyncio>=0.21.0; extra == "dev"
Requires-Dist: black>=23.0.0; extra == "dev"
Requires-Dist: flake8>=6.0.0; extra == "dev"
Requires-Dist: mypy>=1.0.0; extra == "dev"
Dynamic: author
Dynamic: home-page
Dynamic: license-file
Dynamic: requires-python
